LICENSE
hiddb/__init__.py
hiddb/asynchronous.py
hiddb/config.py
hiddb/synchronous.py
hiddb-0.1.10.dist-info/LICENSE
hiddb-0.1.10.dist-info/WHEEL
hiddb-0.1.10.dist-info/METADATA
hiddb-0.1.10.dist-info/RECORD
