Metadata-Version: 2.1
Name: hiddb
Version: 0.1.10
Summary: Python SDK for HIDDB
Home-page: https://hiddb.com
License: MIT
Keywords: HIDDB,hiddb,vector database,similarity search
Author: Benjamin Bolbrinker
Author-email: benjamin.bolbrinker@hiddb.com
Requires-Python: >=3.7,<4.0
Classifier: License :: OSI Approved :: MIT License
Classifier: Programming Language :: Python :: 3
Classifier: Programming Language :: Python :: 3.10
Classifier: Programming Language :: Python :: 3.7
Classifier: Programming Language :: Python :: 3.8
Classifier: Programming Language :: Python :: 3.9
Requires-Dist: PyJWT (>=2.3.0,<3.0.0)
Requires-Dist: aiohttp (>=3.8.1,<4.0.0)
Requires-Dist: asyncio (>=3.4.3,<4.0.0)
Requires-Dist: pytest-asyncio (>=0.18.3,<0.19.0)
Requires-Dist: requests (>=2.27.1,<3.0.0)
Requires-Dist: urllib3 (>=1.26.9,<2.0.0)
Project-URL: Repository, https://github.com/hiddb/hiddb-sdk-py.git
